github_activity/__init__.py
github_activity/auth.py
github_activity/cache.py
github_activity/cli.py
github_activity/git.py
github_activity/github_activity.py
github_activity/graphql.py
github_activity-1.1.5.dist-info/METADATA
github_activity-1.1.5.dist-info/WHEEL
github_activity-1.1.5.dist-info/entry_points.txt
github_activity-1.1.5.dist-info/top_level.txt
github_activity-1.1.5.dist-info/RECORD
