Metadata-Version: 2.4
Name: github_activity
Version: 1.1.5
Summary: Grab recent issue/PR activity from a GitHub repository and render it as markdown.
Author-email: Executable Books Project <executablebooks@gmail.com>
License-Expression: BSD-3-Clause
Project-URL: Homepage, https://executablebooks.org
Project-URL: Source, https://github.com/executablebooks/github-activity
Keywords: Development,Changelog
Requires-Python: >=3.9
Requires-Dist: markdown
Requires-Dist: numpy
Requires-Dist: pandas
Requires-Dist: python-dateutil
Requires-Dist: pytz
Requires-Dist: requests
Requires-Dist: tqdm
Provides-Extra: testing
Requires-Dist: pytest; extra == "testing"
Requires-Dist: pytest-regressions; extra == "testing"
Provides-Extra: sphinx
Requires-Dist: sphinx; extra == "sphinx"
Requires-Dist: myst_parser; extra == "sphinx"
Requires-Dist: sphinx_book_theme; extra == "sphinx"
